aider/__init__.py
aider/__main__.py
aider/args.py
aider/args_formatter.py
aider/commands.py
aider/diffs.py
aider/dump.py
aider/gui.py
aider/help.py
aider/help_pats.py
aider/history.py
aider/io.py
aider/linter.py
aider/llm.py
aider/main.py
aider/mdstream.py
aider/models.py
aider/prompts.py
aider/repo.py
aider/repomap.py
aider/scrape.py
aider/sendchat.py
aider/urls.py
aider/utils.py
aider/versioncheck.py
aider/voice.py
aider/coders/__init__.py
aider/coders/ask_coder.py
aider/coders/ask_prompts.py
aider/coders/base_coder.py
aider/coders/base_prompts.py
aider/coders/editblock_coder.py
aider/coders/editblock_fenced_coder.py
aider/coders/editblock_fenced_prompts.py
aider/coders/editblock_func_coder.py
aider/coders/editblock_func_prompts.py
aider/coders/editblock_prompts.py
aider/coders/help_coder.py
aider/coders/help_prompts.py
aider/coders/search_replace.py
aider/coders/single_wholefile_func_coder.py
aider/coders/single_wholefile_func_prompts.py
aider/coders/udiff_coder.py
aider/coders/udiff_prompts.py
aider/coders/wholefile_coder.py
aider/coders/wholefile_func_coder.py
aider/coders/wholefile_func_prompts.py
aider/coders/wholefile_prompts.py
tt_945-2024.3.17.dist-info/LICENSE.txt
tt_945-2024.3.17.dist-info/METADATA
tt_945-2024.3.17.dist-info/WHEEL
tt_945-2024.3.17.dist-info/entry_points.txt
tt_945-2024.3.17.dist-info/top_level.txt
tt_945-2024.3.17.dist-info/RECORD
