Metadata-Version: 2.1
Name: tt-945
Version: 2024.3.17
Summary: AI Software Engineer
Requires-Python: >=3.9,<3.13
License-File: LICENSE.txt
Requires-Dist: aiohappyeyeballs==2.3.4
Requires-Dist: aiohttp==3.10.0
Requires-Dist: aiosignal==1.3.1
Requires-Dist: annotated-types==0.7.0
Requires-Dist: anyio==4.4.0
Requires-Dist: attrs==23.2.0
Requires-Dist: backoff==2.2.1
Requires-Dist: beautifulsoup4==4.12.3
Requires-Dist: certifi==2024.7.4
Requires-Dist: cffi==1.16.0
Requires-Dist: charset-normalizer==3.3.2
Requires-Dist: click==8.1.7
Requires-Dist: configargparse==1.7
Requires-Dist: diff-match-patch==20230430
Requires-Dist: diskcache==5.6.3
Requires-Dist: distro==1.9.0
Requires-Dist: filelock==3.15.4
Requires-Dist: flake8==7.1.0
Requires-Dist: frozenlist==1.4.1
Requires-Dist: fsspec==2024.6.1
Requires-Dist: gitdb==4.0.11
Requires-Dist: gitpython==3.1.43
Requires-Dist: grep-ast==0.3.3
Requires-Dist: h11==0.14.0
Requires-Dist: httpcore==1.0.5
Requires-Dist: httpx==0.27.0
Requires-Dist: huggingface-hub==0.24.5
Requires-Dist: idna==3.7
Requires-Dist: importlib-metadata==7.2.1
Requires-Dist: importlib-resources==6.4.0
Requires-Dist: jinja2==3.1.4
Requires-Dist: jsonschema==4.23.0
Requires-Dist: jsonschema-specifications==2023.12.1
Requires-Dist: litellm==1.42.9
Requires-Dist: markdown-it-py==3.0.0
Requires-Dist: markupsafe==2.1.5
Requires-Dist: mccabe==0.7.0
Requires-Dist: mdurl==0.1.2
Requires-Dist: multidict==6.0.5
Requires-Dist: networkx==3.2.1
Requires-Dist: numpy==1.26.4
Requires-Dist: openai==1.37.2
Requires-Dist: packaging==24.1
Requires-Dist: pathspec==0.12.1
Requires-Dist: pillow==10.4.0
Requires-Dist: prompt-toolkit==3.0.47
Requires-Dist: pycodestyle==2.12.0
Requires-Dist: pycparser==2.22
Requires-Dist: pydantic==2.8.2
Requires-Dist: pydantic-core==2.20.1
Requires-Dist: pyflakes==3.2.0
Requires-Dist: pygments==2.18.0
Requires-Dist: pypandoc==1.13
Requires-Dist: python-dotenv==1.0.1
Requires-Dist: pyyaml==6.0.1
Requires-Dist: referencing==0.35.1
Requires-Dist: regex==2024.7.24
Requires-Dist: requests==2.32.3
Requires-Dist: rich==13.7.1
Requires-Dist: rpds-py==0.19.1
Requires-Dist: scipy==1.13.1
Requires-Dist: smmap==5.0.1
Requires-Dist: sniffio==1.3.1
Requires-Dist: sounddevice==0.4.7
Requires-Dist: soundfile==0.12.1
Requires-Dist: soupsieve==2.5
Requires-Dist: tiktoken==0.7.0
Requires-Dist: tokenizers==0.19.1
Requires-Dist: tqdm==4.66.4
Requires-Dist: tree-sitter==0.21.3
Requires-Dist: tree-sitter-languages==1.10.2
Requires-Dist: typing-extensions==4.12.2
Requires-Dist: urllib3==2.2.2
Requires-Dist: wcwidth==0.2.13
Requires-Dist: yarl==1.9.4
Requires-Dist: zipp==3.19.2
